.hgignore
.installed.cfg
.project
.pydevproject
LICENSE
MANIFEST.in
README.txt
bootstrap.py
buildout.cfg
setup.py
bin/buildout
docs/HISTORY.txt
docs/README.txt
src/ztfy/__init__.py
src/ztfy.skin.egg-info/PKG-INFO
src/ztfy.skin.egg-info/SOURCES.txt
src/ztfy.skin.egg-info/dependency_links.txt
src/ztfy.skin.egg-info/entry_points.txt
src/ztfy.skin.egg-info/namespace_packages.txt
src/ztfy.skin.egg-info/not-zip-safe
src/ztfy.skin.egg-info/requires.txt
src/ztfy.skin.egg-info/top_level.txt
src/ztfy/skin/README.txt
src/ztfy/skin/__init__.py
src/ztfy/skin/configure.zcml
src/ztfy/skin/container.py
src/ztfy/skin/container.zcml
src/ztfy/skin/content.py
src/ztfy/skin/content.zcml
src/ztfy/skin/form.py
src/ztfy/skin/form.zcml
src/ztfy/skin/layer.py
src/ztfy/skin/menu.py
src/ztfy/skin/metas.py
src/ztfy/skin/namespace.py
src/ztfy/skin/oid.py
src/ztfy/skin/overrides.zcml
src/ztfy/skin/page.py
src/ztfy/skin/presentation.py
src/ztfy/skin/security.py
src/ztfy/skin/security.zcml
src/ztfy/skin/skin.py
src/ztfy/skin/skin.zcml
src/ztfy/skin/terms.py
src/ztfy/skin/viewlet.py
src/ztfy/skin/widget.py
src/ztfy/skin/widget.zcml
src/ztfy/skin/doctests/README.txt
src/ztfy/skin/interfaces/__init__.py
src/ztfy/skin/interfaces/container.py
src/ztfy/skin/interfaces/metas.py
src/ztfy/skin/locales/ztfy.skin.pot
src/ztfy/skin/locales/en/LC_MESSAGES/ztfy.skin.mo
src/ztfy/skin/locales/en/LC_MESSAGES/ztfy.skin.po
src/ztfy/skin/locales/fr/LC_MESSAGES/ztfy.skin.mo
src/ztfy/skin/locales/fr/LC_MESSAGES/ztfy.skin.po
src/ztfy/skin/resources/css/ztfy.skin.css
src/ztfy/skin/resources/css/ztfy.skin.min.css
src/ztfy/skin/resources/img/favicon.png
src/ztfy/skin/resources/img/glyphicons-halflings-white.png
src/ztfy/skin/resources/img/glyphicons-halflings.png
src/ztfy/skin/resources/img/loading-icon.gif
src/ztfy/skin/resources/img/loading.gif
src/ztfy/skin/resources/img/menu-active.png
src/ztfy/skin/resources/img/mi.png
src/ztfy/skin/resources/img/next.gif
src/ztfy/skin/resources/img/pl.png
src/ztfy/skin/resources/img/sort.png
src/ztfy/skin/resources/js/ztfy.skin.js
src/ztfy/skin/resources/js/ztfy.skin.min.js
src/ztfy/skin/resources/js/i18n/fr.js
src/ztfy/skin/resources/js/i18n/fr.min.js
src/ztfy/skin/templates/layout.pt
src/ztfy/skin/templates/login_layout.pt
src/ztfy/skin/templates/progress.pt
