Metadata-Version: 1.1
Name: ztfy.skin
Version: 0.6.22
Summary: ZTFY skin utility package, including views, forms and viewlets base classes
Home-page: http://www.ztfy.org
Author: Thierry Florac
Author-email: tflorac@ulthar.net
License: ZPL
Keywords: ZTFY Zope3 skin
Platform: UNKNOWN
Classifier: License :: OSI Approved :: Zope Public License
Classifier: Development Status :: 4 - Beta
Classifier: Programming Language :: Python
Classifier: Framework :: Zope3
Classifier: Topic :: Software Development :: Libraries :: Python Modules
